Workbook

Sheet Léeme
B2: Proyecto interdisciplinar 1.º ESO · Tiendas de Barrio
B4: Para qué es | C4: Para ir metiendo aquí lo que cada materia aporta al proyecto, con sus criterios, sus fechas y su estado. Es el mismo mural A3 del kit en papel, pero editable entre todos.
B5: Cómo se usa | C5: Archivo → Abrir con Google Sheets. Compártelo con permiso de edición al equipo. Cada docente rellena su fila en la hoja «Aportaciones» y marca su estado.
B6: Hojas | C6: Calendario (qué toca cada semana) · Mural (materias × fases) · Aportaciones (el detalle, con desplegables) · Criterios (los 300 criterios de 1.º ESO) · Materias · Panel (recuento automático).
B7: Desplegables | C7: Las celdas con flecha traen lista: materia, tramo, fase, criterio, instrumento y estado. El texto del criterio aparece solo al elegir su código.
B8: Colores e iconos | C8: Cada materia tiene el color y el emoji que usa la web y los PDF. Cada criterio lleva el emoji de la acción que desarrolla: el mismo emoji en dos materias significa la misma acción, y ahí hay una conexión.
B9: Las fórmulas | C9: Se calculan al abrir el archivo en Google Sheets o Excel. Si ves celdas vacías en «Panel» antes de abrirlo del todo, es normal.
B10: Fuente del currículo | C10: Orden de 30 de mayo de 2023 (BOJA n.º 104), Anexo II; BOE para Religión. No se ha reescrito nada a mano.
B11: Dudas | C11: Juan María Gámez Ortiz · juan.gamez@iesalandalus.org
B13: Leyenda de materias
B14: 🔢 MAT | C14: Matemáticas · Materias comunes · 23 criterios
B15: 📖 LCL | C15: Lengua Castellana y Literatura · Materias comunes · 22 criterios
B16: 🌐 LEX | C16: Inglés · Materias comunes · 16 criterios
B17: 🗺️ GEH | C17: Geografía e Historia · Materias comunes · 30 criterios
B18: 🔬 BYG | C18: Biología y Geología · Materias comunes · 19 criterios
B19: 🏃 EFI | C19: Educación Física · Materias comunes · 17 criterios
B20: 🎨 EPV | C20: Educación Plástica, Visual y Audiovisual · Materias comunes · 22 criterios
B21: 🎵 MUS | C21: Música · Materias comunes · 10 criterios
B22: 🤖 CYR | C22: Computación y Robótica · Optativas · 15 criterios
B23: 🏛️ CCL | C23: Cultura Clásica · Optativas · 26 criterios
B24: 🎙️ OYD | C24: Oratoria y Debate · Optativas · 20 criterios
B25: 🇫🇷 SLE | C25: Francés · Optativas · 16 criterios
... B29: 🌙 RIS | C29: Religión Islámica · Religión · 14 criterios

Sheet Calendario
A1: Calendario de planificación · entrega los viernes · el aula es en noviembre y diciembre
A2: Tramo | B2: Qué se pide | C2: Desde | D2: Hasta | E2: Entrega | F2: Objetivo | G2: Estado | H2: Notas del equipo
A3: T1 | B3: Me apunto — Ficha de compromiso de tu materia | C3: 46293.917 | D3: 46296.917 | E3: 46296.917 | F3: Saber quién entra, en qué fase del aula y con qué idea. (15 min por docente) | G3: Pendiente
A4: T2 | B4: Mi currículo — Ficha curricular de tu materia | C4: 46299.917 | D4: 46303.917 | E4: 46303.917 | F4: Anclar tu tarea a criterios de evaluación reales, con su evidencia y su instrumento. (25 min por docente) | G4: Pendiente
A5: T3 | B5: Encajamos — Ficha de acuerdos y fechas | C5: 46307.917 | D5: 46310.917 | E5: 46310.917 | F5: Acordar qué recibe y qué entrega cada materia, y en qué fecha. (20 min por docente) | G5: Pendiente
A6: T4 | B6: Mi sesión — Guion de sesión y material | C6: 46313.917 | D6: 46317.917 | E6: 46317.917 | F6: Dejar la sesión minutada y el material del alumnado listo para noviembre. (40 min por docente) | G6: Pendiente
A7: Cierre | B7: Cierre y calendario de aula | C7: 46320.958 | E7: 46320.958 | F7: Reunión de una hora: proyecto completo, calendario de sesiones y acuerdos firmados. | G7: Pendiente
A9: En el aula · las seis fases con el alumnado
A10: Fase | B10: Nombre | C10: Sesiones | F10: Qué pasa y qué deja | G10: Estado | H10: Quién entra
A11: 🏷️ 1 | B11: Nuestra tienda | C11: 2–3 | F11: Presentar el reto, formar equipos y repartir roles. Elegir tipo de tienda, productos y clientela. Deja: Identidad de la tienda y catálogo. | G11: Pendiente
A12: 🧾 2 | B12: Pedidos y cambio | C12: 4–5 | F12: Calcular precios, cantidades, importes y cambio con números decimales. Deja: Pedido o factura comprobados. | G12: Pendiente
A13: ％ 3 | B13: Ofertas con sentido | C13: 3–4 | F13: Descuentos, promociones e impuestos. Comparar ofertas y decidir. Deja: Oferta explicada con sus condiciones. | G13: Pendiente
A14: 🏪 4 | B14: Primer mercado | C14: 1–2 | F14: Pedido a proveedores con presupuesto limitado y primer mercado simulado. Deja: Registro de ventas. | G14: Pendiente
A15: 📊 5 | B15: Los datos nos ayudan | C15: 3–4 | F15: Organizar las ventas en tablas y gráficos, e interpretarlas. Deja: Una decisión basada en datos. | G15: Pendiente
A16: 🎤 6 | B16: Mejoramos y contamos | C16: 2–3 | F16: Segundo mercado con mejoras. Portfolio y presentación final. Deja: Portfolio y presentación de 4–6 min. | G16: Pendiente

Sheet Mural
A1: Mural del equipo · qué aporta cada materia en cada fase
A2: El texto gris es la idea propuesta: bórralo y escribe la aportación real cuando la materia la confirme.
A3: Materia | C3: 🏷️ 1 · Nuestra tienda | D3: 🧾 2 · Pedidos y cambio | E3: ％ 3 · Ofertas con sentido | F3: 🏪 4 · Primer mercado | G3: 📊 5 · Los datos nos ayudan | H3: 🎤 6 · Mejoramos y contamos | I3: 🏔️ Otro reto
A4: Matemáticas | B4: 🔢 | C4: Equipos, roles y portfolio | D4: Un pedido sin errores · CE 1 y 2 | E4: Porcentajes y ofertas | F4: Pedido con presupuesto | G4: Lo que dicen las ventas · CE 7 y 8 | H4: Balance y presentación
A5: Lengua Castellana | B5: 📖 | D5: Cómo se lee una factura · CE 5 | H5: Contamos lo que hicimos · CE 3
A6: Inglés | B6: 🌐 | C6: Mini catalogue · CE 2 | F6: At the shop · CE 3
A7: Geografía e Historia | B7: 🗺️ | C7: Dónde abrimos la tienda · CE 4 y 1 | H7: Barrio o gran superficie · CE 2
A8: Biología y Geología | B8: 🔬 | C8: Envases con cabeza · CE 5 | G8: ¿Cuánto residuo evitamos? · CE 5 y 1
A9: Educación Física | B9: 🏃 | C9: Tienda de material deportivo · CE 1 | F9: Un mercado seguro · CE 5
A10: Plástica y Audiovisual | B10: 🎨 | C10: Un logotipo que se reconoce · CE 7 | E10: Un cartel en cinco segundos · CE 5 y 8
A11: Música | B11: 🎵 | E11: Cuña de 15 segundos · CE 4 | F11: El ambiente del mercado · CE 1
A12: Computación y Robótica | B12: 🤖 | D12: Caja registradora en bloques · CE 2 | G12: Del registro al patrón · CE 4
A13: Cultura Clásica | B13: 🏛️ | C13: Del ágora y el foro al barrio · CE 1 | E13: Mercurio y la moneda · CE 6 y 4
A14: Oratoria y Debate | B14: 🎙️ | E14: Vender sin engañar · CE 1 y 3 | H14: Debate de cierre · CE 5
A15: Francés | B15: 🇫🇷 | C15: La vitrine · CE 2 | F15: Au marché · CE 3
A16: Área Lingüística | B16: ✍️ | C16: Leemos el catálogo · CE 4 | E16: Una oferta que diga la verdad · CE 5
A17: Religión Católica | B17: ⛪ | E17: ¿Es justa esta oferta? · CE 3 | H17: Una tienda que cuida · CE 2
A18: Religión Evangélica | B18: 📕 | E18: Comercio honrado · CE 4 | H18: Una tienda que cuida · CE 4
A19: Religión Islámica | B19: 🌙 | C19: Los zocos de Al-Ándalus · CE 3 | H19: Un barrio de muchas culturas · CE 1
A20: Orientación · PT | C20: Transversal: anticipar barreras, graduar catálogos y apoyar dentro del aula.

Sheet Aportaciones
A1: Aportaciones · una fila por aportación. Las celdas con flecha tienen desplegable.
A2: Materia | C2: Tramo | D2: Fase del aula | E2: Tarea del alumnado | F2: Criterio 1 | G2: Texto del criterio 1 | H2: Criterio 2 | I2: Texto del criterio 2 | J2: Saberes | K2: Evidencia individual | L2: Instrumento | M2: Ses. | N2: Min. | O2: Recibo de | P2: Entrego a | Q2: Fecha de entrega | R2: Estado | S2: Enlace al material
A3: Matemáticas | B3: =IFERROR(INDEX(Materias!$C$3:$C$18,MATCH($A3,Materias!$B$3:$B$18,0)),"") | C3: T2 | D3: 2 · Pedidos y cambio | E3: EJEMPLO (bórralo): calcular el pedido de la tienda con 5 €, comprobar el cambio y explicar la revisión a otra pareja. | F3: MAT.1.1.3 | G3: =IFERROR(INDEX(Criterios!$H$3:$H$302,MATCH($F3,Criterios!$C$3:$C$302,0)),"") | H3: MAT.1.2.2 | I3: =IFERROR(INDEX(Criterios!$H$3:$H$302,MATCH($H3,Criterios!$C$3:$C$302,0)),"") | J3: A.2.2 · A.3.4 | K3: Pedido revisado y registro de comprobación | L3: Lista de cotejo | M3: 4 | N3: 55 | O3: Plástica y Audiovisual | P3: Lengua Castellana | Q3: 46338.958 | R3: Enviada
B4: =IFERROR(INDEX(Materias!$C$3:$C$18,MATCH($A4,Materias!$B$3:$B$18,0)),"") | G4: =IFERROR(INDEX(Criterios!$H$3:$H$302,MATCH($F4,Criterios!$C$3:$C$302,0)),"") | I4: =IFERROR(INDEX(Criterios!$H$3:$H$302,MATCH($H4,Criterios!$C$3:$C$302,0)),"")
B5: =IFERROR(INDEX(Materias!$C$3:$C$18,MATCH($A5,Materias!$B$3:$B$18,0)),"") | G5: =IFERROR(INDEX(Criterios!$H$3:$H$302,MATCH($F5,Criterios!$C$3:$C$302,0)),"") | I5: =IFERROR(INDEX(Criterios!$H$3:$H$302,MATCH($H5,Criterios!$C$3:$C$302,0)),"")
B6: =IFERROR(INDEX(Materias!$C$3:$C$18,MATCH($A6,Materias!$B$3:$B$18,0)),"") | G6: =IFERROR(INDEX(Criterios!$H$3:$H$302,MATCH($F6,Criterios!$C$3:$C$302,0)),"") | I6: =IFERROR(INDEX(Criterios!$H$3:$H$302,MATCH($H6,Criterios!$C$3:$C$302,0)),"")
B7: =IFERROR(INDEX(Materias!$C$3:$C$18,MATCH($A7,Materias!$B$3:$B$18,0)),"") | G7: =IFERROR(INDEX(Criterios!$H$3:$H$302,MATCH($F7,Criterios!$C$3:$C$302,0)),"") | I7: =IFERROR(INDEX(Criterios!$H$3:$H$302,MATCH($H7,Criterios!$C$3:$C$302,0)),"")
B8: =IFERROR(INDEX(Materias!$C$3:$C$18,MATCH($A8,Materias!$B$3:$B$18,0)),"") | G8: =IFERROR(INDEX(Criterios!$H$3:$H$302,MATCH($F8,Criterios!$C$3:$C$302,0)),"") | I8: =IFERROR(INDEX(Criterios!$H$3:$H$302,MATCH($H8,Criterios!$C$3:$C$302,0)),"")
B9: =IFERROR(INDEX(Materias!$C$3:$C$18,MATCH($A9,Materias!$B$3:$B$18,0)),"") | G9: =IFERROR(INDEX(Criterios!$H$3:$H$302,MATCH($F9,Criterios!$C$3:$C$302,0)),"") | I9: =IFERROR(INDEX(Criterios!$H$3:$H$302,MATCH($H9,Criterios!$C$3:$C$302,0)),"")
B10: =IFERROR(INDEX(Materias!$C$3:$C$18,MATCH($A10,Materias!$B$3:$B$18,0)),"") | G10: =IFERROR(INDEX(Criterios!$H$3:$H$302,MATCH($F10,Criterios!$C$3:$C$302,0)),"") | I10: =IFERROR(INDEX(Criterios!$H$3:$H$302,MATCH($H10,Criterios!$C$3:$C$302,0)),"")
B11: =IFERROR(INDEX(Materias!$C$3:$C$18,MATCH($A11,Materias!$B$3:$B$18,0)),"") | G11: =IFERROR(INDEX(Criterios!$H$3:$H$302,MATCH($F11,Criterios!$C$3:$C$302,0)),"") | I11: =IFERROR(INDEX(Criterios!$H$3:$H$302,MATCH($H11,Criterios!$C$3:$C$302,0)),"")
B12: =IFERROR(INDEX(Materias!$C$3:$C$18,MATCH($A12,Materias!$B$3:$B$18,0)),"") | G12: =IFERROR(INDEX(Criterios!$H$3:$H$302,MATCH($F12,Criterios!$C$3:$C$302,0)),"") | I12: =IFERROR(INDEX(Criterios!$H$3:$H$302,MATCH($H12,Criterios!$C$3:$C$302,0)),"")
B13: =IFERROR(INDEX(Materias!$C$3:$C$18,MATCH($A13,Materias!$B$3:$B$18,0)),"") | G13: =IFERROR(INDEX(Criterios!$H$3:$H$302,MATCH($F13,Criterios!$C$3:$C$302,0)),"") | I13: =IFERROR(INDEX(Criterios!$H$3:$H$302,MATCH($H13,Criterios!$C$3:$C$302,0)),"")
B14: =IFERROR(INDEX(Materias!$C$3:$C$18,MATCH($A14,Materias!$B$3:$B$18,0)),"") | G14: =IFERROR(INDEX(Criterios!$H$3:$H$302,MATCH($F14,Criterios!$C$3:$C$302,0)),"") | I14: =IFERROR(INDEX(Criterios!$H$3:$H$302,MATCH($H14,Criterios!$C$3:$C$302,0)),"")
B15: =IFERROR(INDEX(Materias!$C$3:$C$18,MATCH($A15,Materias!$B$3:$B$18,0)),"") | G15: =IFERROR(INDEX(Criterios!$H$3:$H$302,MATCH($F15,Criterios!$C$3:$C$302,0)),"") | I15: =IFERROR(INDEX(Criterios!$H$3:$H$302,MATCH($H15,Criterios!$C$3:$C$302,0)),"")
... B160: =IFERROR(INDEX(Materias!$C$3:$C$18,MATCH($A160,Materias!$B$3:$B$18,0)),"") | G160: =IFERROR(INDEX(Criterios!$H$3:$H$302,MATCH($F160,Criterios!$C$3:$C$302,0)),"") | I160: =IFERROR(INDEX(Criterios!$H$3:$H$302,MATCH($H160,Criterios!$C$3:$C$302,0)),"")

Sheet Criterios
A1: Los 300 criterios de 1.º ESO · fuente: Orden de 30 de mayo de 2023 (BOJA n.º 104) y BOE para Religión
A2: Materia | C2: Código | D2: Nº | E2: CE | F2: Acción que desarrolla | H2: Texto completo del criterio | I2: Saberes relacionados
A3: Matemáticas | B3: 🔢 | C3: MAT.1.1.1 | D3: 1.1 | E3: 1 | F3: Resolver problemas | G3: 🧩 | H3: Iniciarse en la interpretación de problemas matemáticos sencillos, reconociendo los datos dados, estableciendo, de manera básica, las relaciones entre ellos y comprendiendo las preguntas formuladas. | I3: A.2.1 · A.2.3 · E.1.2
A4: Matemáticas | B4: 🔢 | C4: MAT.1.1.2 | D4: 1.2 | E4: 1 | F4: Resolver problemas | G4: 🧩 | H4: Aplicar, en problemas de contextos cercanos de la vida cotidiana, herramientas y estrategias apropiadas, como pueden ser la descomposición en problemas más sencillos, el tanteo, el ensayo y error o la búsqueda de patrones, que contribuyan a la resolución de problemas de su entorno más cercano. | I4: A.3.1 · B.1.2
A5: Matemáticas | B5: 🔢 | C5: MAT.1.1.3 | D5: 1.3 | E5: 1 | F5: Resolver problemas | G5: 🧩 | H5: Obtener las soluciones matemáticas en problemas de contextos cercanos de la vida cotidiana, activando los conocimientos necesarios, aceptando el error como parte del proceso. | I5: A.2.2 · A.3.4 · F.1.3
A6: Matemáticas | B6: 🔢 | C6: MAT.1.2.1 | D6: 2.1 | E6: 2 | F6: Razonar y comprobar | G6: ✅ | H6: Comprobar, de forma razonada la corrección de las soluciones de un problema, usando herramientas digitales como calculadoras, hojas de cálculo o programas específicos. | I6: A.3.5
A7: Matemáticas | B7: 🔢 | C7: MAT.1.2.2 | D7: 2.2 | E7: 2 | F7: Razonar y comprobar | G7: ✅ | H7: Comprobar, mediante la lectura comprensiva, la validez de las soluciones obtenidas en un problema comprobando su coherencia en el contexto planteado y evaluando el alcance y repercusión de estas soluciones desde diferentes perspectivas: igualdad de género, sostenibilidad, consumo responsable, equidad o no discriminación. | I7: A.6 · B.2 · F.3.2
A8: Matemáticas | B8: 🔢 | C8: MAT.1.3.1 | D8: 3.1 | E8: 3 | F8: Razonar y comprobar | G8: ✅ | H8: Formular y comprobar conjeturas sencillas en situaciones del entorno cercano, de forma guiada, trabajando de forma individual o colectiva la utilización del razonamiento inductivo para formular argumentos matemáticos, analizando patrones, propiedades y relaciones. | I8: A.3.3 · B.1.1
A9: Matemáticas | B9: 🔢 | C9: MAT.1.3.2 | D9: 3.2 | E9: 3 | F9: Razonar y comprobar | G9: ✅ | H9: Plantear, en términos matemáticos, variantes de un problema dado, en contextos cercanos de la vida cotidiana, modificando alguno de sus datos o alguna condición del problema, enriqueciendo así los conceptos matemáticos. | I9: D.4.2
A10: Matemáticas | B10: 🔢 | C10: MAT.1.3.3 | D10: 3.3 | E10: 3 | F10: Razonar y comprobar | G10: ✅ | H10: Emplear herramientas tecnológicas adecuadas, calculadoras o software matemáticos como paquetes estadísticos o programas de análisis numérico en la investigación y comprobación de conjeturas o problemas. | I10: E.2.2
A11: Matemáticas | B11: 🔢 | C11: MAT.1.4.1 | D11: 4.1 | E11: 4 | F11: Pensamiento computacional | G11: 🧠 | H11: Reconocer patrones en la resolución de problemas sencillos, organizar datos y descomponer un problema en partes más simples, facilitando su interpretación computacional y relacionando los aspectos básicos de la informática con las necesidades del alumnado. | I11: A.1.1
A12: Matemáticas | B12: 🔢 | C12: MAT.1.4.2 | D12: 4.2 | E12: 4 | F12: Pensamiento computacional | G12: 🧠 | H12: Modelizar situaciones del entorno cercano y resolver problemas sencillos de forma eficaz, interpretando y modificando algoritmos, creando modelos de situaciones cotidianas. | I12: D.1 · D.2
A13: Matemáticas | B13: 🔢 | C13: MAT.1.5.1 | D13: 5.1 | E13: 5 | F13: Conectar saberes y contextos | G13: 🔗 | H13: Reconocer y usar las relaciones entre los conocimientos y experiencias matemáticas de los bloques de saberes formando un todo coherente, reconociendo y utilizando las conexiones entre ideas matemáticas en la resolución de problemas sencillos del entorno cercano. | I13: A.3.2
A14: Matemáticas | B14: 🔢 | C14: MAT.1.5.2 | D14: 5.2 | E14: 5 | F14: Conectar saberes y contextos | G14: 🔗 | H14: Realizar conexiones entre diferentes procesos matemáticos sencillos, aplicando conocimientos y experiencias previas y enlazándolas con las nuevas ideas. | I14: A.2.5 · A.4.1
... A302: Religión Islámica | B302: 🌙 | C302: RIS.12.3.4 | D302: 3.4 | E302: 3 | F302: Sociedades en el tiempo | G302: ⏳ | H302: Ubicar geográfica y cronológicamente el periodo de la Sirah en la historia del Islam y seleccionar algunas situaciones del Profeta (P.B) que proporcionen información significativa sobre su actitud ante las ideas contrarias de las demás personas durante el periodo de la Prédica, sintetizando las decisiones clave mediante trabajo grupal y utilizando varias fuentes y plataformas de información. | I302: C.3 · C.7

Sheet Materias
A1: Materias del proyecto · esta hoja alimenta los desplegables: no cambies el orden de las columnas
A2: Código | B2: Materia | C2: Icono | D2: Grupo | E2: Criterios | F2: Competencias | G2: Saberes | H2: Color | I2: Ideas de partida
A3: MAT | B3: Matemáticas | C3: 🔢 | D3: Materias comunes | E3: 23 | F3: 10 | G3: 53 | H3: #0369a1 | I3: F2: Un pedido sin errores · F5: Lo que dicen las ventas
A4: LCL | B4: Lengua Castellana | C4: 📖 | D4: Materias comunes | E4: 22 | F4: 10 | G4: 38 | H4: #be123c | I4: F2: Cómo se lee una factura · F6: Contamos lo que hicimos
A5: LEX | B5: Inglés | C5: 🌐 | D5: Materias comunes | E5: 16 | F5: 6 | G5: 23 | H5: #6d28d9 | I5: F1: Mini catalogue · F4: At the shop
A6: GEH | B6: Geografía e Historia | C6: 🗺️ | D6: Materias comunes | E6: 30 | F6: 9 | G6: 32 | H6: #047857 | I6: F1: Dónde abrimos la tienda · F6: Barrio o gran superficie
A7: BYG | B7: Biología y Geología | C7: 🔬 | D7: Materias comunes | E7: 19 | F7: 6 | G7: 34 | H7: #4d7c0f | I7: F1: Envases con cabeza · F5: ¿Cuánto residuo evitamos?
A8: EFI | B8: Educación Física | C8: 🏃 | D8: Materias comunes | E8: 17 | F8: 5 | G8: 49 | H8: #c2410c | I8: F1: Tienda de material deportivo · F4: Un mercado seguro
A9: EPV | B9: Plástica y Audiovisual | C9: 🎨 | D9: Materias comunes | E9: 22 | F9: 8 | G9: 13 | H9: #b45309 | I9: F1: Un logotipo que se reconoce · F3: Un cartel en cinco segundos
A10: MUS | B10: Música | C10: 🎵 | D10: Materias comunes | E10: 10 | F10: 4 | G10: 21 | H10: #a21caf | I10: F3: Cuña de 15 segundos · F4: El ambiente del mercado
A11: CYR | B11: Computación y Robótica | C11: 🤖 | D11: Optativas | E11: 15 | F11: 6 | G11: 41 | H11: #4f46e5 | I11: F2: Caja registradora en bloques · F5: Del registro al patrón
A12: CCL | B12: Cultura Clásica | C12: 🏛️ | D12: Optativas | E12: 26 | F12: 6 | G12: 35 | H12: #991b1b | I12: F1: Del ágora y el foro al barrio · F3: Mercurio y la moneda
A13: OYD | B13: Oratoria y Debate | C13: 🎙️ | D13: Optativas | E13: 20 | F13: 5 | G13: 21 | H13: #0e7490 | I13: F3: Vender sin engañar · F6: Debate de cierre
A14: SLE | B14: Francés | C14: 🇫🇷 | D14: Optativas | E14: 16 | F14: 6 | G14: 23 | H14: #7e22ce | I14: F1: La vitrine · F4: Au marché
... A18: RIS | B18: Religión Islámica | C18: 🌙 | D18: Religión | E18: 14 | F18: 3 | G18: 37 | H18: #57534e | I18: F1: Los zocos de Al-Ándalus · F6: Un barrio de muchas culturas

Sheet Panel
B2: Panel · se calcula solo desde la hoja «Aportaciones»
B4: Por tramo | C4: Apuntadas | D4: Enviadas | E4: Revisadas | H4: Qué mirar
B5: T1 · Me apunto | C5: =COUNTIF(Aportaciones!$C$4:$C$160,"T1") | D5: =COUNTIFS(Aportaciones!$C$4:$C$160,"T1",Aportaciones!$R$4:$R$160,"Enviada") | E5: =COUNTIFS(Aportaciones!$C$4:$C$160,"T1",Aportaciones!$R$4:$R$160,"Revisada") | H5: Sin esto no se puede repartir nada: la fase 2 del aula necesita saber quién produce el catálogo y quién lo usa.
B6: T2 · Mi currículo | C6: =COUNTIF(Aportaciones!$C$4:$C$160,"T2") | D6: =COUNTIFS(Aportaciones!$C$4:$C$160,"T2",Aportaciones!$R$4:$R$160,"Enviada") | E6: =COUNTIFS(Aportaciones!$C$4:$C$160,"T2",Aportaciones!$R$4:$R$160,"Revisada") | H6: Una aportación sin criterio es una actividad suelta: no se evalúa y no cuenta para tu programación.
B7: T3 · Encajamos | C7: =COUNTIF(Aportaciones!$C$4:$C$160,"T3") | D7: =COUNTIFS(Aportaciones!$C$4:$C$160,"T3",Aportaciones!$R$4:$R$160,"Enviada") | E7: =COUNTIFS(Aportaciones!$C$4:$C$160,"T3",Aportaciones!$R$4:$R$160,"Revisada") | H7: Aquí es donde un proyecto interdisciplinar se cae: alguien espera un material que nadie se comprometió a entregar.
B8: T4 · Mi sesión | C8: =COUNTIF(Aportaciones!$C$4:$C$160,"T4") | D8: =COUNTIFS(Aportaciones!$C$4:$C$160,"T4",Aportaciones!$R$4:$R$160,"Enviada") | E8: =COUNTIFS(Aportaciones!$C$4:$C$160,"T4",Aportaciones!$R$4:$R$160,"Revisada") | H8: Si el material se prepara en noviembre, se prepara mal o no se prepara.
B11: Por materia | C11: Filas | D11: Enviadas | E11: Sesiones | F11: Minutos | H11: Ideas de partida
B12: Matemáticas | C12: =COUNTIF(Aportaciones!$A$4:$A$160,"Matemáticas") | D12: =COUNTIFS(Aportaciones!$A$4:$A$160,"Matemáticas",Aportaciones!$R$4:$R$160,"Enviada") | E12: =SUMIF(Aportaciones!$A$4:$A$160,"Matemáticas",Aportaciones!$M$4:$M$160) | F12: =SUMPRODUCT((Aportaciones!$A$4:$A$160="Matemáticas")*Aportaciones!$M$4:$M$160*Aportaciones!$N$4:$N$160) | H12: Un pedido sin errores · Lo que dicen las ventas
B13: Lengua Castellana | C13: =COUNTIF(Aportaciones!$A$4:$A$160,"Lengua Castellana") | D13: =COUNTIFS(Aportaciones!$A$4:$A$160,"Lengua Castellana",Aportaciones!$R$4:$R$160,"Enviada") | E13: =SUMIF(Aportaciones!$A$4:$A$160,"Lengua Castellana",Aportaciones!$M$4:$M$160) | F13: =SUMPRODUCT((Aportaciones!$A$4:$A$160="Lengua Castellana")*Aportaciones!$M$4:$M$160*Aportaciones!$N$4:$N$160) | H13: Cómo se lee una factura · Contamos lo que hicimos
B14: Inglés | C14: =COUNTIF(Aportaciones!$A$4:$A$160,"Inglés") | D14: =COUNTIFS(Aportaciones!$A$4:$A$160,"Inglés",Aportaciones!$R$4:$R$160,"Enviada") | E14: =SUMIF(Aportaciones!$A$4:$A$160,"Inglés",Aportaciones!$M$4:$M$160) | F14: =SUMPRODUCT((Aportaciones!$A$4:$A$160="Inglés")*Aportaciones!$M$4:$M$160*Aportaciones!$N$4:$N$160) | H14: Mini catalogue · At the shop
B15: Geografía e Historia | C15: =COUNTIF(Aportaciones!$A$4:$A$160,"Geografía e Historia") | D15: =COUNTIFS(Aportaciones!$A$4:$A$160,"Geografía e Historia",Aportaciones!$R$4:$R$160,"Enviada") | E15: =SUMIF(Aportaciones!$A$4:$A$160,"Geografía e Historia",Aportaciones!$M$4:$M$160) | F15: =SUMPRODUCT((Aportaciones!$A$4:$A$160="Geografía e Historia")*Aportaciones!$M$4:$M$160*Aportaciones!$N$4:$N$160) | H15: Dónde abrimos la tienda · Barrio o gran superficie
B16: Biología y Geología | C16: =COUNTIF(Aportaciones!$A$4:$A$160,"Biología y Geología") | D16: =COUNTIFS(Aportaciones!$A$4:$A$160,"Biología y Geología",Aportaciones!$R$4:$R$160,"Enviada") | E16: =SUMIF(Aportaciones!$A$4:$A$160,"Biología y Geología",Aportaciones!$M$4:$M$160) | F16: =SUMPRODUCT((Aportaciones!$A$4:$A$160="Biología y Geología")*Aportaciones!$M$4:$M$160*Aportaciones!$N$4:$N$160) | H16: Envases con cabeza · ¿Cuánto residuo evitamos?
B17: Educación Física | C17: =COUNTIF(Aportaciones!$A$4:$A$160,"Educación Física") | D17: =COUNTIFS(Aportaciones!$A$4:$A$160,"Educación Física",Aportaciones!$R$4:$R$160,"Enviada") | E17: =SUMIF(Aportaciones!$A$4:$A$160,"Educación Física",Aportaciones!$M$4:$M$160) | F17: =SUMPRODUCT((Aportaciones!$A$4:$A$160="Educación Física")*Aportaciones!$M$4:$M$160*Aportaciones!$N$4:$N$160) | H17: Tienda de material deportivo · Un mercado seguro
B18: Plástica y Audiovisual | C18: =COUNTIF(Aportaciones!$A$4:$A$160,"Plástica y Audiovisual") | D18: =COUNTIFS(Aportaciones!$A$4:$A$160,"Plástica y Audiovisual",Aportaciones!$R$4:$R$160,"Enviada") | E18: =SUMIF(Aportaciones!$A$4:$A$160,"Plástica y Audiovisual",Aportaciones!$M$4:$M$160) | F18: =SUMPRODUCT((Aportaciones!$A$4:$A$160="Plástica y Audiovisual")*Aportaciones!$M$4:$M$160*Aportaciones!$N$4:$N$160) | H18: Un logotipo que se reconoce · Un cartel en cinco segundos
B19: Música | C19: =COUNTIF(Aportaciones!$A$4:$A$160,"Música") | D19: =COUNTIFS(Aportaciones!$A$4:$A$160,"Música",Aportaciones!$R$4:$R$160,"Enviada") | E19: =SUMIF(Aportaciones!$A$4:$A$160,"Música",Aportaciones!$M$4:$M$160) | F19: =SUMPRODUCT((Aportaciones!$A$4:$A$160="Música")*Aportaciones!$M$4:$M$160*Aportaciones!$N$4:$N$160) | H19: Cuña de 15 segundos · El ambiente del mercado
B20: Computación y Robótica | C20: =COUNTIF(Aportaciones!$A$4:$A$160,"Computación y Robótica") | D20: =COUNTIFS(Aportaciones!$A$4:$A$160,"Computación y Robótica",Aportaciones!$R$4:$R$160,"Enviada") | E20: =SUMIF(Aportaciones!$A$4:$A$160,"Computación y Robótica",Aportaciones!$M$4:$M$160) | F20: =SUMPRODUCT((Aportaciones!$A$4:$A$160="Computación y Robótica")*Aportaciones!$M$4:$M$160*Aportaciones!$N$4:$N$160) | H20: Caja registradora en bloques · Del registro al patrón
B21: Cultura Clásica | C21: =COUNTIF(Aportaciones!$A$4:$A$160,"Cultura Clásica") | D21: =COUNTIFS(Aportaciones!$A$4:$A$160,"Cultura Clásica",Aportaciones!$R$4:$R$160,"Enviada") | E21: =SUMIF(Aportaciones!$A$4:$A$160,"Cultura Clásica",Aportaciones!$M$4:$M$160) | F21: =SUMPRODUCT((Aportaciones!$A$4:$A$160="Cultura Clásica")*Aportaciones!$M$4:$M$160*Aportaciones!$N$4:$N$160) | H21: Del ágora y el foro al barrio · Mercurio y la moneda
B22: Oratoria y Debate | C22: =COUNTIF(Aportaciones!$A$4:$A$160,"Oratoria y Debate") | D22: =COUNTIFS(Aportaciones!$A$4:$A$160,"Oratoria y Debate",Aportaciones!$R$4:$R$160,"Enviada") | E22: =SUMIF(Aportaciones!$A$4:$A$160,"Oratoria y Debate",Aportaciones!$M$4:$M$160) | F22: =SUMPRODUCT((Aportaciones!$A$4:$A$160="Oratoria y Debate")*Aportaciones!$M$4:$M$160*Aportaciones!$N$4:$N$160) | H22: Vender sin engañar · Debate de cierre
B23: Francés | C23: =COUNTIF(Aportaciones!$A$4:$A$160,"Francés") | D23: =COUNTIFS(Aportaciones!$A$4:$A$160,"Francés",Aportaciones!$R$4:$R$160,"Enviada") | E23: =SUMIF(Aportaciones!$A$4:$A$160,"Francés",Aportaciones!$M$4:$M$160) | F23: =SUMPRODUCT((Aportaciones!$A$4:$A$160="Francés")*Aportaciones!$M$4:$M$160*Aportaciones!$N$4:$N$160) | H23: La vitrine · Au marché
B24: Área Lingüística | C24: =COUNTIF(Aportaciones!$A$4:$A$160,"Área Lingüística") | D24: =COUNTIFS(Aportaciones!$A$4:$A$160,"Área Lingüística",Aportaciones!$R$4:$R$160,"Enviada") | E24: =SUMIF(Aportaciones!$A$4:$A$160,"Área Lingüística",Aportaciones!$M$4:$M$160) | F24: =SUMPRODUCT((Aportaciones!$A$4:$A$160="Área Lingüística")*Aportaciones!$M$4:$M$160*Aportaciones!$N$4:$N$160) | H24: Leemos el catálogo · Una oferta que diga la verdad
B25: Religión Católica | C25: =COUNTIF(Aportaciones!$A$4:$A$160,"Religión Católica") | D25: =COUNTIFS(Aportaciones!$A$4:$A$160,"Religión Católica",Aportaciones!$R$4:$R$160,"Enviada") | E25: =SUMIF(Aportaciones!$A$4:$A$160,"Religión Católica",Aportaciones!$M$4:$M$160) | F25: =SUMPRODUCT((Aportaciones!$A$4:$A$160="Religión Católica")*Aportaciones!$M$4:$M$160*Aportaciones!$N$4:$N$160) | H25: ¿Es justa esta oferta? · Una tienda que cuida
B26: Religión Evangélica | C26: =COUNTIF(Aportaciones!$A$4:$A$160,"Religión Evangélica") | D26: =COUNTIFS(Aportaciones!$A$4:$A$160,"Religión Evangélica",Aportaciones!$R$4:$R$160,"Enviada") | E26: =SUMIF(Aportaciones!$A$4:$A$160,"Religión Evangélica",Aportaciones!$M$4:$M$160) | F26: =SUMPRODUCT((Aportaciones!$A$4:$A$160="Religión Evangélica")*Aportaciones!$M$4:$M$160*Aportaciones!$N$4:$N$160) | H26: Comercio honrado · Una tienda que cuida
B27: Religión Islámica | C27: =COUNTIF(Aportaciones!$A$4:$A$160,"Religión Islámica") | D27: =COUNTIFS(Aportaciones!$A$4:$A$160,"Religión Islámica",Aportaciones!$R$4:$R$160,"Enviada") | E27: =SUMIF(Aportaciones!$A$4:$A$160,"Religión Islámica",Aportaciones!$M$4:$M$160) | F27: =SUMPRODUCT((Aportaciones!$A$4:$A$160="Religión Islámica")*Aportaciones!$M$4:$M$160*Aportaciones!$N$4:$N$160) | H27: Los zocos de Al-Ándalus · Un barrio de muchas culturas
B30: Por fase del aula | C30: Aportaciones | H30: Qué deja la fase
B31: 🏷️ 1 · Nuestra tienda | C31: =COUNTIF(Aportaciones!$D$4:$D$160,"1 · Nuestra tienda") | H31: Identidad de la tienda y catálogo
B32: 🧾 2 · Pedidos y cambio | C32: =COUNTIF(Aportaciones!$D$4:$D$160,"2 · Pedidos y cambio") | H32: Pedido o factura comprobados
B33: ％ 3 · Ofertas con sentido | C33: =COUNTIF(Aportaciones!$D$4:$D$160,"3 · Ofertas con sentido") | H33: Oferta explicada con sus condiciones
B34: 🏪 4 · Primer mercado | C34: =COUNTIF(Aportaciones!$D$4:$D$160,"4 · Primer mercado") | H34: Registro de ventas
B35: 📊 5 · Los datos nos ayudan | C35: =COUNTIF(Aportaciones!$D$4:$D$160,"5 · Los datos nos ayudan") | H35: Una decisión basada en datos
B36: 🎤 6 · Mejoramos y contamos | C36: =COUNTIF(Aportaciones!$D$4:$D$160,"6 · Mejoramos y contamos") | H36: Portfolio y presentación de 4–6 min
B38: Los recuentos ignoran la fila de ejemplo (fila 3). Bórrala cuando empiecen a entrar datos reales.
